AppSafe/__init__.py
AppSafe/appsafe.py
AppSafe/core/__init__.py
AppSafe/core/agent.py
AppSafe/core/applock.py
AppSafe/core/auth.py
AppSafe-1.2.16.dist-info/LICENSE
AppSafe-1.2.16.dist-info/METADATA
AppSafe-1.2.16.dist-info/WHEEL
AppSafe-1.2.16.dist-info/entry_points.txt
AppSafe-1.2.16.dist-info/top_level.txt
AppSafe-1.2.16.dist-info/RECORD
