Metadata-Version: 2.1
Name: AppSafe
Version: 1.2.16
Summary: A Simple python AppLocker and FileLocker
Home-page: UNKNOWN
Author: Xeroxxhah (Muhammad Nauman Azeem)
Author-email: xeroxxhah@pm.me
License: UNKNOWN
Keywords: python,python3,FileLock,AppLock,linux
Platform: UNKNOWN
Classifier: Development Status :: 1 - Planning
Classifier: Intended Audience :: Developers
Classifier: Programming Language :: Python :: 3
Classifier: Operating System :: Unix
Classifier: Operating System :: MacOS :: MacOS X
License-File: LICENSE
Requires-Dist: easygui
Requires-Dist: pyAesCrypt
